mplcairo.pth
mplcairo/_mplcairo.cpython-39-darwin.so
mplcairo/gtk.py
mplcairo/qt.py
mplcairo/__init__.py
mplcairo/macosx.py
mplcairo/tk.py
mplcairo/.gitignore
mplcairo/_util.py
mplcairo/gtk_native.py
mplcairo/multipage.py
mplcairo/base.py
mplcairo/_backports.py
mplcairo/wx.py
mplcairo-0.6.1.dist-info/RECORD
mplcairo-0.6.1.dist-info/WHEEL
mplcairo-0.6.1.dist-info/top_level.txt
mplcairo-0.6.1.dist-info/LICENSE.txt
mplcairo-0.6.1.dist-info/METADATA
