Metadata-Version: 2.1
Name: mplcairo
Version: 0.6.1
Summary: A (new) cairo backend for Matplotlib.
Author: Antony Lee
License: MIT
Classifier: Development Status :: 4 - Beta
Classifier: Framework :: Matplotlib
Classifier: License :: OSI Approved :: MIT License
Classifier: Programming Language :: Python :: 3
Requires-Python: >=3.8
License-File: LICENSE.txt
Requires-Dist: matplotlib >=2.2
Requires-Dist: pillow
Requires-Dist: pycairo >=1.16.0 ; os_name == "posix"
